{"data":[
    {"tip": "Rig Veda, Book 1, Chapter 31", "body": "Rishi Hiranyastupa Angiras's Mantra on Agni recited in Jagati Chhand meter. "},
    {"tip": "Sanskrit", "body": "प्रथमं मण्डलमं, अनु ७, ३१ सूक्तम् ऋषि: हरिण्यस्तुप आन्गिरासः छन्द: जगती अग्निः देव"},
    {"tip": "Mantra 1.31.10", "body": "त्वमग्ने प्रमतिस्त्वं पितासि नस्त्वं वयस्कृत्तव जामयो वयम । सं त्वा रायः शतिनः सं सहस्रिणः सुवीरं यन्ति व्रतपामदाभ्य ॥ "},
    {"tip": "Transliterated", "body": "tvamagne pramatih tvam pita asi nah tvam vayah-a-krt tava jamayah vayam; sam tva rayah shatinah sam sahasrinah su-a-viram yanti vrata-a-pam adabhya"},
    {"tip": "Word by word", "body": "tvam agne (you, agni) pramatih tvam (you come first to thought) pita asi (father) nah tvam vayah-a-krt (preserving health) tava (yours) jamayah (sibling) vayam (we); sam (with) tva (you) rayah (prince) shatinah (hundred) sam (with) sahasrinah (sahasra - innumerable) su-a-viram (main hero) yanti (sam yanti - reach you) vrata-a-pam (vrita - law of workings) adabhya (adabhya - severe)"}
]}
